AUTHORS
ChangeLog
LICENSE
README.rst
requirements.txt
run_tests.sh
setup.cfg
setup.py
test-requirements.txt
tox.ini
fuel_tasks_validator.egg-info/PKG-INFO
fuel_tasks_validator.egg-info/SOURCES.txt
fuel_tasks_validator.egg-info/dependency_links.txt
fuel_tasks_validator.egg-info/entry_points.txt
fuel_tasks_validator.egg-info/not-zip-safe
fuel_tasks_validator.egg-info/pbr.json
fuel_tasks_validator.egg-info/requires.txt
fuel_tasks_validator.egg-info/top_level.txt
tasks_validator/__init__.py
tasks_validator/consts.py
tasks_validator/graph.py
tasks_validator/schemas.py
tasks_validator/setup_hooks.py
tasks_validator/validator.py
tasks_validator/visualization.py
tasks_validator/tests/.gitkeep
tasks_validator/tests/__init__.py
tasks_validator/tests/test_graph.py
tasks_validator/tests/test_validator.py
tasks_validator/tests/test_visualization.py