Metadata-Version: 1.1
Name: fuel-tasks-validator
Version: 6.1.0
Summary: Tasks validation for Fuel
Home-page: http://mirantis.com
Author: Mirantis Inc.
Author-email: product@mirantis.com
License: UNKNOWN
Platform: UNKNOWN
Classifier: Intended Audience :: Developers
Classifier: Intended Audience :: Information Technology
Classifier: License :: OSI Approved :: Apache Software License
Classifier: Operating System :: POSIX :: Linux
Classifier: Programming Language :: Python
Classifier: Programming Language :: Python :: 2
Classifier: Programming Language :: Python :: 2.6
